llama_index/readers/github/__init__.py
llama_index/readers/github/collaborators/__init__.py
llama_index/readers/github/collaborators/base.py
llama_index/readers/github/collaborators/github_client.py
llama_index/readers/github/issues/__init__.py
llama_index/readers/github/issues/base.py
llama_index/readers/github/issues/github_client.py
llama_index/readers/github/repository/__init__.py
llama_index/readers/github/repository/base.py
llama_index/readers/github/repository/event.py
llama_index/readers/github/repository/github_client.py
llama_index/readers/github/repository/utils.py
llama_index_readers_github-0.8.2.dist-info/METADATA
llama_index_readers_github-0.8.2.dist-info/WHEEL
llama_index_readers_github-0.8.2.dist-info/licenses/LICENSE
llama_index_readers_github-0.8.2.dist-info/RECORD
