Metadata-Version: 2.4
Name: llama-index-readers-github
Version: 0.8.2
Summary: llama-index readers github integration
Author-email: Your Name <you@example.com>
Maintainer: ahmetkca, moncho, rwood-97
License-Expression: MIT
License-File: LICENSE
Keywords: code,collaborators,git,github,issues,placeholder,repository,source code
Requires-Python: <4.0,>=3.9
Requires-Dist: httpx>=0.26.0
Requires-Dist: llama-index-core<0.15,>=0.13.0
Requires-Dist: llama-index-readers-file<0.6,>=0.5.0
